py_crave_gui/__init__.py
py_crave_gui/window.py
py_crave_gui/components/__init__.py
py_crave_gui/components/button.py
py_crave_gui/components/checkbox.py
py_crave_gui/components/combobox.py
py_crave_gui/components/entry.py
py_crave_gui/components/label.py
py_crave_gui/components/listbox.py
py_crave_gui/components/menubar.py
py_crave_gui/components/progressbar.py
py_crave_gui/components/radiobutton.py
py_crave_gui/components/slider.py
py_crave_gui/components/theme.py
py_crave_gui/components/tooltip.py
py_crave_gui-0.3.3.dist-info/METADATA
py_crave_gui-0.3.3.dist-info/WHEEL
py_crave_gui-0.3.3.dist-info/top_level.txt
py_crave_gui-0.3.3.dist-info/RECORD
