Metadata-Version: 2.1
Name: py-crave-gui
Version: 0.3.3
Summary: A GUI library with customizable components for Python.
Author: Julox Games
Classifier: Programming Language :: Python :: 3
Classifier: License :: OSI Approved :: MIT License
Classifier: Operating System :: OS Independent
Requires-Python: >=3.6
Requires-Dist: py-crave-sync
